sunagent_app/__init__.py
sunagent_app/__main__.py
sunagent_app/_constants.py
sunagent_app/metrics.py
sunagent_app/py.typed
sunagent_app/sunpump_service.py
sunagent_app/agents/__init__.py
sunagent_app/agents/_context_builder_agent.py
sunagent_app/agents/_http_utils.py
sunagent_app/agents/_image_analysis_agent.py
sunagent_app/agents/_image_generate_agent.py
sunagent_app/agents/_image_utils.py
sunagent_app/agents/_markdown_utils.py
sunagent_app/agents/_token_launch_agent.py
sunagent_app/agents/_tweet_analysis_agent.py
sunagent_app/agents/_tweet_check_agent.py
sunagent_app/memory/__init__.py
sunagent_app/memory/_knowledge_memory.py
sunagent_app/memory/_profile_memory.py
sunagent_app/templates/token_templates.py
sunagent_app/templates/twitter_templates.py
sunagent_app/utils/__init__.py
sunagent_app/utils/ratelimit.py
sunagent_app-0.0.24.dist-info/METADATA
sunagent_app-0.0.24.dist-info/WHEEL
sunagent_app-0.0.24.dist-info/entry_points.txt
sunagent_app-0.0.24.dist-info/licenses/LICENSE-CODE
sunagent_app-0.0.24.dist-info/RECORD
