Metadata-Version: 2.4
Name: sunagent-app
Version: 0.0.24
Summary: sunagent app
License:     MIT License
License-File: LICENSE-CODE
Classifier: License :: OSI Approved :: MIT License
Classifier: Operating System :: OS Independent
Classifier: Programming Language :: Python :: 3
Requires-Python: >=3.12
Requires-Dist: apscheduler
Requires-Dist: async-lru
Requires-Dist: autogen
Requires-Dist: autogen-agentchat
Requires-Dist: autogen-core
Requires-Dist: autogen-ext
Requires-Dist: flask-cors
Requires-Dist: flask[async]
Requires-Dist: google-genai
Requires-Dist: openpyxl
Requires-Dist: prometheus-client
Requires-Dist: pytz
Requires-Dist: quart
Requires-Dist: sunagent-ext
Requires-Dist: tweepy
